MANIFEST.in
README
README.rst
setup.py
django_paymecash.egg-info/PKG-INFO
django_paymecash.egg-info/SOURCES.txt
django_paymecash.egg-info/dependency_links.txt
django_paymecash.egg-info/requires.txt
django_paymecash.egg-info/top_level.txt
example/__init__.py
example/__init__.pyc
example/manage.py
example/manage.pyc
example/paymecash.log
example/settings.py
example/settings.pyc
example/settings_local.py
example/settings_local.pyc
example/urls.py
example/urls.pyc
example/views.py
example/views.pyc
example/wsgi.py
example/wsgi.pyc
example/cart/__init__.py
example/cart/__init__.pyc
example/cart/admin.py
example/cart/admin.pyc
example/cart/models.py
example/cart/models.pyc
example/templates/pay_page.html
paymecash/__init__.py
paymecash/__init__.pyc
paymecash/admin.py
paymecash/admin.pyc
paymecash/common.py
paymecash/common.pyc
paymecash/conf.py
paymecash/conf.pyc
paymecash/forms.py
paymecash/forms.pyc
paymecash/models.py
paymecash/models.pyc
paymecash/signals.py
paymecash/signals.pyc
paymecash/tests.py
paymecash/urls.py
paymecash/urls.pyc
paymecash/views.py
paymecash/views.pyc
paymecash/migrations/0001_initial.py
paymecash/migrations/0001_initial.pyc
paymecash/migrations/__init__.py
paymecash/migrations/__init__.pyc