Metadata-Version: 1.0
Name: django-paymecash
Version: 0.0.3
Summary: It's application for pay-system Paymecash.py
Home-page: http://github.com/drmartiner/django-paymecash/
Author: Alexey Kuzmin
Author-email: DrMartiner@GMail.Com
License: MIT
Platform: UNKNOWN
Classifier: Environment :: Web Environment
Classifier: Framework :: Django
Classifier: Intended Audience :: Developers
Classifier: License :: OSI Approved :: MIT License
Classifier: Operating System :: OS Independent
Classifier: Programming Language :: Python
Classifier: Programming Language :: Python :: 2.6
Classifier: Programming Language :: Python :: 2.7
Classifier: Topic :: Internet :: WWW/HTTP
Classifier: Topic :: Internet :: WWW/HTTP :: Dynamic Content
